lmms_eval/__init__.py
lmms_eval/__main__.py
lmms_eval/evaluator.py
lmms_eval/evaluator_utils.py
lmms_eval/logging_utils.py
lmms_eval/protocol.py
lmms_eval/utils.py
lmms_eval/api/__init__.py
lmms_eval/api/filter.py
lmms_eval/api/group.py
lmms_eval/api/instance.py
lmms_eval/api/metrics.py
lmms_eval/api/model.py
lmms_eval/api/registry.py
lmms_eval/api/samplers.py
lmms_eval/api/task.py
lmms_eval/caching/__init__.py
lmms_eval/caching/cache.py
lmms_eval/filters/__init__.py
lmms_eval/filters/decontamination.py
lmms_eval/filters/extraction.py
lmms_eval/filters/selection.py
lmms_eval/filters/transformation.py
lmms_eval/llm_judge/__init__.py
lmms_eval/llm_judge/base.py
lmms_eval/llm_judge/factory.py
lmms_eval/llm_judge/prompt.py
lmms_eval/llm_judge/protocol.py
lmms_eval/llm_judge/utils.py
lmms_eval/llm_judge/launcher/__init__.py
lmms_eval/llm_judge/launcher/base.py
lmms_eval/llm_judge/launcher/sglang.py
lmms_eval/llm_judge/providers/__init__.py
lmms_eval/llm_judge/providers/async_azure_openai.py
lmms_eval/llm_judge/providers/async_openai.py
lmms_eval/llm_judge/providers/azure_openai.py
lmms_eval/llm_judge/providers/dummy.py
lmms_eval/llm_judge/providers/openai.py
lmms_eval/loggers/__init__.py
lmms_eval/loggers/evaluation_tracker.py
lmms_eval/loggers/utils.py
lmms_eval/loggers/wandb_logger.py
lmms_eval/mcp/__init__.py
lmms_eval/mcp/client.py
lmms_eval/models/__init__.py
lmms_eval/models/chat/async_openai.py
lmms_eval/models/chat/huggingface.py
lmms_eval/models/chat/llava_hf.py
lmms_eval/models/chat/longvila.py
lmms_eval/models/chat/openai_compatible.py
lmms_eval/models/chat/qwen2_5_vl.py
lmms_eval/models/chat/sglang.py
lmms_eval/models/chat/thyme.py
lmms_eval/models/chat/vllm.py
lmms_eval/models/model_utils/__init__.py
lmms_eval/models/model_utils/audio_processing.py
lmms_eval/models/model_utils/gen_metrics.py
lmms_eval/models/model_utils/load_video.py
lmms_eval/models/model_utils/reasoning_model_utils.py
lmms_eval/models/model_utils/qwen/qwen_generate_utils.py
lmms_eval-0.5.0.dist-info/licenses/LICENSE
lmms_eval-0.5.0.dist-info/METADATA
lmms_eval-0.5.0.dist-info/WHEEL
lmms_eval-0.5.0.dist-info/entry_points.txt
lmms_eval-0.5.0.dist-info/top_level.txt
lmms_eval-0.5.0.dist-info/RECORD
