Metadata-Version: 2.4
Name: lmms_eval
Version: 0.5.0
Summary: A framework for evaluating large multi-modality language models
Author-email: LMMMs-Lab Evaluation Team <lmms-lab@outlook.com>
License-Expression: MIT
Project-URL: Homepage, https://lmms-lab.github.io
Project-URL: Repository, https://github.com/EvolvingLMMs-Lab/lmms-eval
Classifier: Programming Language :: Python :: 3
Classifier: Operating System :: OS Independent
Requires-Python: >=3.9
License-File: LICENSE
Requires-Dist: accelerate>=0.29.1
Requires-Dist: black>=24.1.0
Requires-Dist: isort>=5.13.2
Requires-Dist: datasets>=2.19.0
Requires-Dist: evaluate>=0.4.0
Requires-Dist: httpx==0.23.3
Requires-Dist: jsonlines
Requires-Dist: numexpr
Requires-Dist: numpy==1.26.4
Requires-Dist: peft>=0.2.0
Requires-Dist: pybind11>=2.6.2
Requires-Dist: pytablewriter
Requires-Dist: sacrebleu>=1.5.0
Requires-Dist: scikit-learn>=0.24.1
Requires-Dist: sqlitedict==2.1.0
Requires-Dist: torch>=2.1.0
Requires-Dist: torchvision>=0.16.0
Requires-Dist: timm
Requires-Dist: einops
Requires-Dist: ftfy
Requires-Dist: openai
Requires-Dist: opencv-python-headless
Requires-Dist: av<16.0.0
Requires-Dist: hf_transfer
Requires-Dist: nltk
Requires-Dist: sentencepiece
Requires-Dist: yt-dlp
Requires-Dist: pycocoevalcap
Requires-Dist: tqdm-multiprocess
Requires-Dist: transformers>=4.39.2
Requires-Dist: transformers-stream-generator
Requires-Dist: zstandard
Requires-Dist: pillow
Requires-Dist: pyyaml
Requires-Dist: sympy
Requires-Dist: latex2sympy2
Requires-Dist: mpmath
Requires-Dist: Jinja2
Requires-Dist: openpyxl
Requires-Dist: loguru
Requires-Dist: hf_transfer
Requires-Dist: tenacity==8.3.0
Requires-Dist: wandb>=0.16.0
Requires-Dist: tiktoken
Requires-Dist: pre-commit
Requires-Dist: pydantic
Requires-Dist: packaging
Requires-Dist: decord; platform_system != "Darwin"
Requires-Dist: eva-decord; platform_system == "Darwin"
Requires-Dist: zss
Requires-Dist: protobuf
Requires-Dist: sentence_transformers
Requires-Dist: python-dotenv
Requires-Dist: qwen-vl-utils>=0.0.14
Provides-Extra: audio
Requires-Dist: more-itertools; extra == "audio"
Requires-Dist: editdistance; extra == "audio"
Requires-Dist: zhconv; extra == "audio"
Requires-Dist: librosa; extra == "audio"
Requires-Dist: soundfile; extra == "audio"
Provides-Extra: metrics
Requires-Dist: pywsd; extra == "metrics"
Requires-Dist: spacy; extra == "metrics"
Requires-Dist: anls; extra == "metrics"
Requires-Dist: rouge; extra == "metrics"
Requires-Dist: capture_metric; extra == "metrics"
Requires-Dist: Levenshtein; extra == "metrics"
Provides-Extra: gemini
Requires-Dist: google-generativeai; extra == "gemini"
Provides-Extra: reka
Requires-Dist: httpx==0.23.3; extra == "reka"
Requires-Dist: reka-api; extra == "reka"
Provides-Extra: qwen
Requires-Dist: decord; extra == "qwen"
Requires-Dist: qwen_vl_utils; extra == "qwen"
Provides-Extra: mmsearch
Requires-Dist: playwright; extra == "mmsearch"
Requires-Dist: requests; extra == "mmsearch"
Requires-Dist: matplotlib; extra == "mmsearch"
Requires-Dist: duckduckgo_search; extra == "mmsearch"
Requires-Dist: langchain; extra == "mmsearch"
Requires-Dist: langchain-community; extra == "mmsearch"
Requires-Dist: beautifulsoup4; extra == "mmsearch"
Requires-Dist: FlagEmbedding; extra == "mmsearch"
Requires-Dist: rouge; extra == "mmsearch"
Dynamic: license-file
